{
  "required": true,
  "minVersion": "0.8",
  "package": "house.greenhouse.rapscallionsandrockhoppers.mixin",
  "refmap": "${mod_id}.refmap.json",
  "compatibilityLevel": "JAVA_21",
  "mixins": [
    "BoatAccessor",
    "BoatMixin",
    "EntityAccessor",
    "EntityMixin",
    "LevelAccessor",
    "LivingEntityMixin",
    "RegistryDataLoaderRegistryDataMixin",
    "VehicleEntityMixin"
  ],
  "client": [
    "client.BoatRendererMixin",
    "client.ClientLevelAccessor"
  ],
  "injectors": {
    "defaultRequire": 1,
    "maxShiftBy": 2
  }
}

